augmolino/__init__.py
augmolino/augmentation.py
augmolino/augmenter.py
augmolino/utils.py
augmolino-0.0.5.dist-info/LICENSE
augmolino-0.0.5.dist-info/METADATA
augmolino-0.0.5.dist-info/WHEEL
augmolino-0.0.5.dist-info/top_level.txt
augmolino-0.0.5.dist-info/RECORD
